{
  "display": {
    "icon": {
      "item": "darkwastes:emberberry"
    },
    "title": "Smells Like Your Father",
    "description": "Collect some emberberries from a scorched tree.",
    "show_toast": true,
    "announce_to_chat": true
  },
  "parent": "darkwastes:dark_wastes/root",
  "criteria": {
    "requirement": {
      "trigger": "minecraft:inventory_changed",
      "conditions": {
        "items": [
          {
            "items": [
              "darkwastes:emberberry"
            ]
          }
        ]
      }
    }
  }
}
